iotile_cloud/__init__.py
iotile_cloud/api/__init__.py
iotile_cloud/api/connection.py
iotile_cloud/api/exceptions.py
iotile_cloud/stream/__init__.py
iotile_cloud/stream/data.py
iotile_cloud/stream/report.py
iotile_cloud/utils/__init__.py
iotile_cloud/utils/basic.py
iotile_cloud/utils/gid.py
iotile_cloud/utils/main.py
iotile_cloud/utils/mdo.py
iotile_cloud/utils/mock_cloud.py
iotile_cloud-0.9.14.dist-info/LICENSE
iotile_cloud-0.9.14.dist-info/METADATA
iotile_cloud-0.9.14.dist-info/WHEEL
iotile_cloud-0.9.14.dist-info/entry_points.txt
iotile_cloud-0.9.14.dist-info/top_level.txt
iotile_cloud-0.9.14.dist-info/RECORD
