Metadata-Version: 2.1
Name: iotile-cloud
Version: 0.9.14
Summary: Python client for https://iotile.cloud
Home-page: https://github.com/iotile/python_iotile_cloud
Author: Arch Systems Inc.
Author-email: info@arch-iot.com
License: MIT
Keywords: iotile,arch,iot,automation
Platform: UNKNOWN
Classifier: Programming Language :: Python
Classifier: Development Status :: 4 - Beta
Classifier: License :: OSI Approved :: MIT License
Classifier: Operating System :: OS Independent
Classifier: Topic :: Software Development :: Libraries :: Python Modules
Requires-Dist: future
Requires-Dist: requests (>=2.21.0)
Requires-Dist: python-dateutil
